odoo/addons/purchase_report_menu_move/README.rst
odoo/addons/purchase_report_menu_move/__init__.py
odoo/addons/purchase_report_menu_move/__manifest__.py
odoo/addons/purchase_report_menu_move/i18n/it.po
odoo/addons/purchase_report_menu_move/i18n/purchase_report_menu_move.pot
odoo/addons/purchase_report_menu_move/readme/CONTRIBUTORS.rst
odoo/addons/purchase_report_menu_move/readme/DESCRIPTION.rst
odoo/addons/purchase_report_menu_move/report/purchase_report_views.xml
odoo/addons/purchase_report_menu_move/static/description/icon.png
odoo/addons/purchase_report_menu_move/static/description/index.html
odoo14_addon_purchase_report_menu_move-14.0.1.0.1.dev6.dist-info/METADATA
odoo14_addon_purchase_report_menu_move-14.0.1.0.1.dev6.dist-info/WHEEL
odoo14_addon_purchase_report_menu_move-14.0.1.0.1.dev6.dist-info/top_level.txt
odoo14_addon_purchase_report_menu_move-14.0.1.0.1.dev6.dist-info/RECORD
